circuitpython_homie/__init__.py
circuitpython_homie/recipes.py
circuitpython_homie-0.1.4.dist-info/LICENSE
circuitpython_homie-0.1.4.dist-info/METADATA
circuitpython_homie-0.1.4.dist-info/WHEEL
circuitpython_homie-0.1.4.dist-info/top_level.txt
circuitpython_homie-0.1.4.dist-info/RECORD
