Metadata-Version: 2.1
Name: circuitpython-homie
Version: 0.1.4
Summary: Homie specifications for MQTT implemented in CircuitPython
Author-email: Brendan Doherty <2bndy5@gmail.com>
License: MIT
Project-URL: Documentation, https://circuitpython-homie.readthedocs.io
Project-URL: Source, https://github.com/2bndy5/CircuitPython_Homie
Project-URL: Tracker, https://github.com/2bndy5/CircuitPython_Homie/issues
Keywords: adafruit,blinka,circuitpython,micropython,homie,MQTT,Homie,CircuitPython
Classifier: Intended Audience :: Developers
Classifier: Topic :: Software Development :: Libraries
Classifier: Topic :: Software Development :: Embedded Systems
Classifier: Topic :: System :: Hardware
Classifier: License :: OSI Approved :: MIT License
Classifier: Programming Language :: Python :: 3
License-File: LICENSE
Requires-Dist: Adafruit-Blinka
Requires-Dist: adafruit-circuitpython-minimqtt
